{"moduleName":"Main","imports":{},"body":[{"tag":"CustomType","name":"Maybe","parameters":["a"],"variants":[{"name":"Just","parameterTypes":[{"tag":"TypeVariable","name":"a","sourceLocation":{"start":{"line":1,"col":21},"end":{"line":1,"col":22}}}]},{"name":"Nothing","parameterTypes":[]}],"sourceLocation":{"start":{"line":1,"col":1},"end":{"line":1,"col":32}}},{"tag":"CustomType","name":"Result","parameters":["error","value"],"variants":[{"name":"Ok","parameterTypes":[{"tag":"TypeVariable","name":"value","sourceLocation":{"start":{"line":3,"col":30},"end":{"line":3,"col":35}}}]},{"name":"Err","parameterTypes":[{"tag":"TypeVariable","name":"error","sourceLocation":{"start":{"line":3,"col":42},"end":{"line":3,"col":47}}}]}],"sourceLocation":{"start":{"line":3,"col":1},"end":{"line":3,"col":47}}},{"tag":"CustomType","name":"List","parameters":["a"],"variants":[{"name":"Nil","parameterTypes":[]},{"name":"Cons","parameterTypes":[{"tag":"TypeVariable","name":"a","sourceLocation":{"start":{"line":5,"col":26},"end":{"line":5,"col":27}}},{"tag":"TypeReference","name":"List","module":null,"arguments":[{"tag":"TypeVariable","name":"a","sourceLocation":{"start":{"line":5,"col":34},"end":{"line":5,"col":35}}}],"sourceLocation":{"start":{"line":5,"col":28},"end":{"line":5,"col":36}}}]}],"sourceLocation":{"start":{"line":5,"col":1},"end":{"line":5,"col":36}}},{"tag":"CustomType","name":"Bool","parameters":[],"variants":[{"name":"True","parameterTypes":[]},{"name":"False","parameterTypes":[]}],"sourceLocation":{"start":{"line":7,"col":1},"end":{"line":7,"col":25}}},{"tag":"Definition","name":"maybeMap____CBR","parameters":[{"pattern":{"tag":"VariableDefinition","name":"f","sourceLocation":{"start":{"line":10,"col":17},"end":{"line":10,"col":18}}},"type":{"tag":"FunctionType","returnType":{"tag":"TypeVariable","name":"b","sourceLocation":{"start":{"line":9,"col":25},"end":{"line":9,"col":26}}},"argumentTypes":[{"tag":"TypeVariable","name":"a","sourceLocation":{"start":{"line":9,"col":20},"end":{"line":9,"col":21}}}],"sourceLocation":{"start":{"line":9,"col":19},"end":{"line":9,"col":27}}}},{"pattern":{"tag":"VariableDefinition","name":"mx","sourceLocation":{"start":{"line":10,"col":19},"end":{"line":10,"col":21}}},"type":{"tag":"TypeReference","name":"Maybe","module":null,"arguments":[{"tag":"TypeVariable","name":"a","sourceLocation":{"start":{"line":9,"col":37},"end":{"line":9,"col":38}}}],"sourceLocation":{"start":{"line":9,"col":31},"end":{"line":9,"col":38}}}}],"returnType":{"tag":"TypeReference","name":"Maybe","module":null,"arguments":[{"tag":"TypeVariable","name":"b","sourceLocation":{"start":{"line":9,"col":48},"end":{"line":9,"col":49}}}],"sourceLocation":{"start":{"line":9,"col":42},"end":{"line":9,"col":49}}},"expression":{"tag":"CaseExpression","subject":{"tag":"VariableReference","name":"mx","sourceLocation":{"start":{"line":11,"col":8},"end":{"line":11,"col":10}}},"branches":[{"pattern":{"tag":"DataPattern","constructor":{"tag":"VariableReference","name":"Just"},"arguments":[{"tag":"VariableDefinition","name":"x","sourceLocation":{"start":{"line":12,"col":10},"end":{"line":12,"col":11}}}],"sourceLocation":{"start":{"line":12,"col":5},"end":{"line":12,"col":11}}},"body":{"tag":"FunctionApplication","function":{"tag":"VariableReference","name":"Just","sourceLocation":{"start":{"line":12,"col":15},"end":{"line":12,"col":19}}},"arguments":[{"tag":"FunctionApplication","function":{"tag":"VariableReference","name":"f","sourceLocation":{"start":{"line":12,"col":21},"end":{"line":12,"col":22}}},"arguments":[{"tag":"VariableReference","name":"x","sourceLocation":{"start":{"line":12,"col":23},"end":{"line":12,"col":24}}}],"sourceLocation":{"start":{"line":12,"col":20},"end":{"line":12,"col":25}}}],"sourceLocation":{"start":{"line":12,"col":15},"end":{"line":12,"col":25}}},"sourceLocation":{"start":{"line":12,"col":5},"end":{"line":12,"col":25}}},{"pattern":{"tag":"DataPattern","constructor":{"tag":"VariableReference","name":"Nothing"},"arguments":[],"sourceLocation":{"start":{"line":13,"col":5},"end":{"line":13,"col":12}}},"body":{"tag":"VariableReference","name":"Nothing","sourceLocation":{"start":{"line":13,"col":16},"end":{"line":13,"col":23}}},"sourceLocation":{"start":{"line":12,"col":25},"end":{"line":13,"col":23}}}],"sourceLocation":{"start":{"line":11,"col":3},"end":{"line":13,"col":23}}},"sourceLocation":{"start":{"line":10,"col":1},"end":{"line":13,"col":23}}},{"tag":"Definition","name":"maybeWithDefault____CBR","parameters":[{"pattern":{"tag":"VariableDefinition","name":"d","sourceLocation":{"start":{"line":16,"col":25},"end":{"line":16,"col":26}}},"type":{"tag":"TypeVariable","name":"a","sourceLocation":{"start":{"line":15,"col":27},"end":{"line":15,"col":28}}}},{"pattern":{"tag":"VariableDefinition","name":"mx","sourceLocation":{"start":{"line":16,"col":27},"end":{"line":16,"col":29}}},"type":{"tag":"TypeReference","name":"Maybe","module":null,"arguments":[{"tag":"TypeVariable","name":"a","sourceLocation":{"start":{"line":15,"col":38},"end":{"line":15,"col":39}}}],"sourceLocation":{"start":{"line":15,"col":32},"end":{"line":15,"col":39}}}}],"returnType":{"tag":"TypeVariable","name":"a","sourceLocation":{"start":{"line":15,"col":43},"end":{"line":15,"col":44}}},"expression":{"tag":"CaseExpression","subject":{"tag":"VariableReference","name":"mx","sourceLocation":{"start":{"line":17,"col":8},"end":{"line":17,"col":10}}},"branches":[{"pattern":{"tag":"DataPattern","constructor":{"tag":"VariableReference","name":"Just"},"arguments":[{"tag":"VariableDefinition","name":"x","sourceLocation":{"start":{"line":18,"col":10},"end":{"line":18,"col":11}}}],"sourceLocation":{"start":{"line":18,"col":5},"end":{"line":18,"col":11}}},"body":{"tag":"VariableReference","name":"x","sourceLocation":{"start":{"line":18,"col":15},"end":{"line":18,"col":16}}},"sourceLocation":{"start":{"line":18,"col":5},"end":{"line":18,"col":16}}},{"pattern":{"tag":"DataPattern","constructor":{"tag":"VariableReference","name":"Nothing"},"arguments":[],"sourceLocation":{"start":{"line":19,"col":5},"end":{"line":19,"col":12}}},"body":{"tag":"VariableReference","name":"d","sourceLocation":{"start":{"line":19,"col":16},"end":{"line":19,"col":17}}},"sourceLocation":{"start":{"line":18,"col":16},"end":{"line":19,"col":17}}}],"sourceLocation":{"start":{"line":17,"col":3},"end":{"line":19,"col":17}}},"sourceLocation":{"start":{"line":16,"col":1},"end":{"line":19,"col":17}}}]}